etf_flow_mcp/__init__.py
etf_flow_mcp/cli.py
etf_flow_mcp-0.1.0.dist-info/METADATA
etf_flow_mcp-0.1.0.dist-info/WHEEL
etf_flow_mcp-0.1.0.dist-info/entry_points.txt
etf_flow_mcp-0.1.0.dist-info/licenses/LICENSE
etf_flow_mcp-0.1.0.dist-info/RECORD
