Metadata-Version: 2.4
Name: etf-flow-mcp
Version: 0.1.0
Summary: An MCP server that delivers crypto ETF flow data to power AI agents' decision-making.
License-File: LICENSE
Requires-Python: >=3.10
Requires-Dist: dotenv>=0.9.9
Requires-Dist: mcp[cli]>=1.6.0
Requires-Dist: pandas>=2.2.3
